balanco/__init__.py
balanco/koho.py
balanco_library-0.2.1.dist-info/LICENSE
balanco_library-0.2.1.dist-info/METADATA
balanco_library-0.2.1.dist-info/WHEEL
balanco_library-0.2.1.dist-info/top_level.txt
balanco_library-0.2.1.dist-info/RECORD
