Metadata-Version: 2.1
Name: balanco-library
Version: 0.2.1
Summary: A simple example package
Home-page: https://github.com/balanco-elias/balanco_library
Author: Elias Isopahkala
Author-email: elias.isopahkala@balanco.fi
License: UNKNOWN
Platform: UNKNOWN
Classifier: Programming Language :: Python :: 3
Classifier: License :: OSI Approved :: MIT License
Classifier: Operating System :: OS Independent
Requires-Python: >=3.6
License-File: LICENSE
Requires-Dist: requests
